adm_osc/__init__.py
adm_osc/client_server.py
adm_osc/handler.py
adm_osc/protocol.py
adm_osc/stable_params.py
adm_osc/stress.py
adm_osc/tests.py
adm_osc-1.0.1.dist-info/LICENSE.txt
adm_osc-1.0.1.dist-info/METADATA
adm_osc-1.0.1.dist-info/WHEEL
adm_osc-1.0.1.dist-info/top_level.txt
adm_osc-1.0.1.dist-info/RECORD
