Metadata-Version: 2.1
Name: adm_osc
Version: 1.0.1
Summary: ADM-OSC client/server Python module for ADM-OSC protocol validation, tests and stress
Home-page: https://github.com/immersive-audio-live/ADM-OSC
Author: Gael Martinet
Author-email: gael@flux.audio
Project-URL: Bug Reports, https://github.com/immersive-audio-live/ADM-OSC/issues
Project-URL: Source, https://github.com/immersive-audio-live/ADM-OSC/
Keywords: adm,osc,clientServer,validation,tests,stress,setuptools,development
Classifier: Development Status :: 5 - Production/Stable
Classifier: Intended Audience :: Developers
Classifier: Topic :: Software Development :: Build Tools
Classifier: License :: OSI Approved :: MIT License
Classifier: Programming Language :: Python :: 3
Classifier: Programming Language :: Python :: 3.6
Classifier: Programming Language :: Python :: 3.7
Classifier: Programming Language :: Python :: 3.8
Classifier: Programming Language :: Python :: 3.9
Classifier: Programming Language :: Python :: 3.10
Classifier: Programming Language :: Python :: 3.11
Classifier: Programming Language :: Python :: 3.12
Classifier: Programming Language :: Python :: 3 :: Only
Requires-Python: >=3.6, <4
License-File: LICENSE.txt
Requires-Dist: peppercorn
Requires-Dist: python-osc
Provides-Extra: dev
Requires-Dist: check-manifest ; extra == 'dev'
Provides-Extra: test
Requires-Dist: coverage ; extra == 'test'
